Metadata-Version: 1.1
Name: py-daemon
Version: 0.1.2
Summary: Python daemonizer for Unix, Linux and OS X
Home-page: https://github.com/serverdensity/python-daemon
Author: Andrey Kulikov
Author-email: amdeich@gmail.com
License: http://creativecommons.org/licenses/by-sa/3.0/
Platform: any
Classifier: License :: OSI Approved :: Attribution Assurance License
Classifier: Intended Audience :: Developers
Classifier: Environment :: No Input/Output (Daemon)
Classifier: Development Status :: 4 - Beta
Classifier: Operating System :: Unix
Classifier: Operating System :: POSIX :: Linux
Classifier: Operating System :: MacOS :: MacOS X
Classifier: Programming Language :: Python :: 2.4
Classifier: Programming Language :: Python :: 2.7
Classifier: Programming Language :: Python :: 3
Classifier: Topic :: Software Development :: Libraries
